tent/__init__.py
tent/exception/__init__.py
tent/exception/github_api_error.py
tent/github/__init__.py
tent/github/app.py
tent/github/client.py
tent/github/config.py
tent/github/expr_parser.py
tent/github/playbook.py
tent/github/response/__init__.py
tent/github/response/action/__init__.py
tent/github/trigger/__init__.py
tent/github/trigger/parser.py
tent/github/trigger/command/__init__.py
tent/github/trigger/event/__init__.py
tent/util/__init__.py
tent/util/file_system.py
tent-0.0.3.dist-info/LICENSE.txt
tent-0.0.3.dist-info/METADATA
tent-0.0.3.dist-info/WHEEL
tent-0.0.3.dist-info/top_level.txt
tent-0.0.3.dist-info/RECORD
