Metadata-Version: 2.1
Name: tent
Version: 0.0.3
Summary: Github Automation Package in Python.
Home-page: https://github.com/clivern/tent/
Author: Clivern
Author-email: hello@clivern.com
License: MIT
Project-URL: Documentation, https://github.com/clivern/tent/
Project-URL: Source, https://github.com/clivern/tent/
Project-URL: Changelog, https://github.com/clivern/tent/blob/main/CHANGELOG.rst
Project-URL: Tracker, https://github.com/clivern/tent/issues
Project-URL: Download, https://pypi.org/project/tent/#files
Platform: any
Classifier: Development Status :: 5 - Production/Stable
Classifier: Programming Language :: Python
Classifier: License :: OSI Approved :: MIT License
License-File: LICENSE.txt
Requires-Dist: PyGithub
Requires-Dist: pyjwt
Requires-Dist: cryptography
Requires-Dist: pycryptodome
Requires-Dist: pyyaml
Requires-Dist: importlib-metadata ; python_version < "3.8"
